insert_db/__init__.py
insert_db/insert_db.py
insert_db-0.0.8.dist-info/METADATA
insert_db-0.0.8.dist-info/WHEEL
insert_db-0.0.8.dist-info/top_level.txt
insert_db-0.0.8.dist-info/RECORD
